odoo/addons/ssi_odoo_implementation_git/README.rst
odoo/addons/ssi_odoo_implementation_git/__init__.py
odoo/addons/ssi_odoo_implementation_git/__manifest__.py
odoo/addons/ssi_odoo_implementation_git/models/__init__.py
odoo/addons/ssi_odoo_implementation_git/models/odoo_module.py
odoo/addons/ssi_odoo_implementation_git/static/description/icon.png
odoo/addons/ssi_odoo_implementation_git/views/odoo_module_views.xml
odoo14_addon_ssi_odoo_implementation_git-14.0.2.0.0.dist-info/METADATA
odoo14_addon_ssi_odoo_implementation_git-14.0.2.0.0.dist-info/WHEEL
odoo14_addon_ssi_odoo_implementation_git-14.0.2.0.0.dist-info/top_level.txt
odoo14_addon_ssi_odoo_implementation_git-14.0.2.0.0.dist-info/RECORD
